tailjlogs/__init__.py
tailjlogs/__main__.py
tailjlogs/cli.py
tailjlogs/find_dialog.py
tailjlogs/format_parser.py
tailjlogs/goto_screen.py
tailjlogs/help.py
tailjlogs/highlighter.py
tailjlogs/line_panel.py
tailjlogs/log_file.py
tailjlogs/log_lines.py
tailjlogs/log_view.py
tailjlogs/messages.py
tailjlogs/poll_watcher.py
tailjlogs/scan_progress_bar.py
tailjlogs/selector_watcher.py
tailjlogs/summary.py
tailjlogs/timestamps.py
tailjlogs/ui.py
tailjlogs/watcher.py
tailjlogs-2.4.1.dist-info/METADATA
tailjlogs-2.4.1.dist-info/WHEEL
tailjlogs-2.4.1.dist-info/entry_points.txt
tailjlogs-2.4.1.dist-info/licenses/LICENSE
tailjlogs-2.4.1.dist-info/RECORD
