Metadata-Version: 2.4
Name: tailjlogs
Version: 2.4.1
Summary: A terminal log file viewer with enhanced JSONL support - based on Toolong
Project-URL: Homepage, https://github.com/brianoflondon/tailjlogs
Project-URL: Repository, https://github.com/brianoflondon/tailjlogs
Project-URL: Bug Tracker, https://github.com/brianoflondon/tailjlogs/issues
Project-URL: Changelog, https://github.com/brianoflondon/tailjlogs/releases
Author-email: Brian of London <brian@brianoflondon.me>
License-Expression: MIT
License-File: LICENSE
Requires-Python: >=3.9
Requires-Dist: click>=8.1.7
Requires-Dist: textual>=1.0.0
Requires-Dist: typing-extensions>=4.9.0
